experimentator/__init__.py
experimentator/__main__.py
experimentator/__version__.py
experimentator/_patched_yaml.py
experimentator/_util.py
experimentator/design.py
experimentator/experiment.py
experimentator/order.py
experimentator/section.py
experimentator-0.3.1.dist-info/DESCRIPTION.rst
experimentator-0.3.1.dist-info/METADATA
experimentator-0.3.1.dist-info/RECORD
experimentator-0.3.1.dist-info/WHEEL
experimentator-0.3.1.dist-info/entry_points.txt
experimentator-0.3.1.dist-info/metadata.json
experimentator-0.3.1.dist-info/top_level.txt
experimentator-0.3.1.dist-info/zip-safe
