Metadata-Version: 2.0
Name: experimentator
Version: 0.3.1
Summary: Experiment builder
Home-page: http://experimentator.readthedocs.org
Author: Henry S. Harrison
Author-email: henry.schafer.harrison@gmail.com
License: MIT
Download-URL: https://bitbucket.org/hharrison/experimentator/get/default.tar.gz
Keywords: experiment science psychology experimental design research
Platform: UNKNOWN
Classifier: Programming Language :: Python
Classifier: Programming Language :: Python :: 3
Classifier: Programming Language :: Python :: 3.3
Classifier: Programming Language :: Python :: 3.4
Classifier: License :: OSI Approved :: MIT License
Classifier: Operating System :: OS Independent
Classifier: Development Status :: 3 - Alpha
Classifier: Intended Audience :: Science/Research
Classifier: Topic :: Scientific/Engineering
Classifier: Topic :: Software Development :: Libraries :: Python Modules
Classifier: Topic :: Utilities
Requires-Dist: docopt
Requires-Dist: networkx
Requires-Dist: numpy
Requires-Dist: pandas
Requires-Dist: pyyaml
Requires-Dist: schema
